[
    {
      "name": "project1",
      "live": "https://smithereens23nas.github.io/Project1-FightClub/",
      "git": "https://github.com/smithereens23nas/Project1-FightClub",
      "image": "https://assets.pokemon.com/static2/_ui/img/og-default-image.jpeg"
    },
    {
      "name": "project2",
      "live": "https://closed-ocean.herokuapp.com/home",
      "git": "https://git.generalassemb.ly/smithereens23nas/closedOcean",
      "image": "https://closed-ocean.herokuapp.com/images/Image.jpg"
    }
  ]